edq_quizcomp_simple_gui-0.1.0.dist-info/licenses/LICENSE
qcg/__init__.py
qcg/common.py
qcg/handlers.py
qcg/project.py
qcg/server.py
qcg/cli/__init__.py
qcg/cli/server.py
qcg/static/__init__.py
qcg/static/favicon.ico
qcg/static/index.html
qcg/static/css/style.css
qcg/static/css/vendor/normalize.css
qcg/static/images/loading-basic-edq.png
qcg/static/js/main.js
qcg/static/js/modules/quizcomp/base.js
qcg/static/js/modules/quizcomp/core.js
qcg/static/js/modules/quizcomp/project.js
qcg/static/js/modules/webui/base.js
qcg/static/js/modules/webui/common.js
qcg/static/js/modules/webui/editor.js
qcg/static/js/modules/webui/log.js
qcg/static/js/modules/webui/project.js
qcg/static/js/modules/webui/render.js
qcg/static/js/modules/webui/util.js
qcg/static/vendor/ace/LICENSE
qcg/static/vendor/ace/ace.js
qcg/static/vendor/ace/mode-html.js
qcg/static/vendor/ace/mode-json5.js
qcg/static/vendor/ace/mode-latex.js
qcg/static/vendor/ace/mode-markdown.js
qcg/static/vendor/ace/mode-text.js
qcg/static/vendor/ace/theme-github.js
qcg/static/vendor/ace/theme-github_dark.js
qcg/static/vendor/goldenlayout/LICENSE-CC-NC-4.0.md
qcg/static/vendor/goldenlayout/LICENSE-GPL-3.0.md
qcg/static/vendor/goldenlayout/goldenlayout-base.css
qcg/static/vendor/goldenlayout/goldenlayout-dark-theme.css
qcg/static/vendor/goldenlayout/goldenlayout-light-theme.css
qcg/static/vendor/goldenlayout/goldenlayout.min.js
qcg/static/vendor/jquery/jquery-3.7.1.min.js
qcg/util/dirent.py
edq_quizcomp_simple_gui-0.1.0.dist-info/METADATA
edq_quizcomp_simple_gui-0.1.0.dist-info/WHEEL
edq_quizcomp_simple_gui-0.1.0.dist-info/top_level.txt
edq_quizcomp_simple_gui-0.1.0.dist-info/RECORD
