Metadata-Version: 2.4
Name: edq-quizcomp-simple-gui
Version: 0.1.0
Summary: A simple GUI for the Quiz Composer meant to be run on a local server.
Author-email: Eriq Augustine <eriq@edulinq.org>
License: MIT License
Project-URL: Homepage, https://github.com/edulinq/quiz-composer-simple-gui
Project-URL: Repository, https://github.com/edulinq/quiz-composer-simple-gui
Keywords: education,quiz,canvas,tex,latex,qti
Classifier: Intended Audience :: Education
Classifier: License :: OSI Approved :: MIT License
Classifier: Programming Language :: Python :: 3.9
Requires-Python: >=3.9
License-File: LICENSE
Requires-Dist: edq-quizcomp>=0.4.0
Provides-Extra: dev
Requires-Dist: build; extra == "dev"
Requires-Dist: packaging>=21.3; extra == "dev"
Requires-Dist: twine; extra == "dev"
Requires-Dist: vermin; extra == "dev"
Dynamic: license-file
